{
  "phase": "phase-131a-release-artifact-preflight",
  "status": "passed",
  "generatedAt": "2026-04-27T16:47:11.759Z",
  "checks": {
    "rootScriptPresent": true,
    "serviceScriptPresent": true,
    "phase129Closed": true,
    "phase130Closed": true,
    "gitTopLevelIsProject": true,
    "localCommitPresent": true,
    "noStagedFiles": true,
    "branchIsMaster": true,
    "remoteConfigured": true,
    "upstreamTracksOriginMaster": true,
    "remoteHeadMatchesLocal": true,
    "repoExists": true,
    "repoIsPrivate": true,
    "latestReleaseGateRecorded": true,
    "latestReleaseGateSucceeded": true,
    "releaseListReadable": true,
    "noGithubReleaseExistsOrLaterPhase134Closed": true,
    "noLocalReleaseTagsOrLaterPhase134Closed": true,
    "laterPhase134ExecutionConsistent": true,
    "workflowHasNoReleaseOrPublishSteps": true,
    "releasePreflightDocPresent": true,
    "releasePreflightDocHasScope": true,
    "releasePreflightDocHasReadOnlyBoundary": true,
    "releasePreflightDocHasManualDecisions": true,
    "readmePhasePresent": true,
    "agentsBoundaryPresent": true,
    "userManualPresent": true,
    "remoteStatusDocPresent": true,
    "noPlainSecrets": true,
    "projectContextNotCreated": true
  },
  "git": {
    "repoRoot": "E:\\AI-Data\\AI网关系统\\unified-ai-system",
    "gitTopLevel": "E:/AI-Data/AI网关系统/unified-ai-system",
    "branch": "master",
    "headSha": "bdba42b600d712acb77926774c75254b8c290ea6",
    "headSubject": "Phase133A release creation confirmation",
    "statusLineCount": 19,
    "statusPreview": [
      "M AGENTS.md",
      "M README.md",
      "M apps/ai-gateway-service/evidence/phase-133a-release-creation-confirmation.json",
      "M apps/ai-gateway-service/evidence/phase-133a-release-creation-confirmation.md",
      "M apps/ai-gateway-service/package.json",
      "M apps/ai-gateway-service/src/entrypoints/verifyGithubReleaseArtifactPreflight.js",
      "M apps/ai-gateway-service/src/entrypoints/verifyReleaseCreationConfirmation.js",
      "M apps/ai-gateway-service/src/entrypoints/verifyReleaseDecisionPack.js",
      "M apps/ai-gateway-service/src/entrypoints/verifyUserManualReleasePack.js",
      "M docs/RELEASE_CREATION_CONFIRMATION.md",
      "M docs/RELEASE_DECISION_PACK.md",
      "M docs/RELEASE_PREFLIGHT.md",
      "M docs/REMOTE_RELEASE_STATUS.md",
      "M docs/USER_MANUAL.md",
      "M package.json",
      "?? apps/ai-gateway-service/evidence/phase-134a-release-creation-execution.json",
      "?? apps/ai-gateway-service/evidence/phase-134a-release-creation-execution.md",
      "?? apps/ai-gateway-service/src/entrypoints/verifyReleaseCreationExecution.js",
      "?? docs/RELEASE_CREATION_EXECUTION.md"
    ],
    "stagedFileCount": 0,
    "localReleaseTagCount": 1,
    "localReleaseTags": [
      "v0.1.0-rc.1"
    ],
    "remoteConfigured": true,
    "remoteLines": [
      "origin\thttps://github.com/happy520ai/unified-ai-system.git (fetch)",
      "origin\thttps://github.com/happy520ai/unified-ai-system.git (push)"
    ],
    "upstream": "origin/master",
    "remoteHeadSha": "bdba42b600d712acb77926774c75254b8c290ea6",
    "remoteHeadMatchesLocal": true
  },
  "github": {
    "repoFullName": "happy520ai/unified-ai-system",
    "repoUrl": "https://github.com/happy520ai/unified-ai-system",
    "isPrivate": true,
    "visibility": "PRIVATE",
    "defaultBranch": "master",
    "latestReleaseGate": {
      "databaseId": 25007359180,
      "workflowName": "Phase117A Release Gate",
      "headBranch": "master",
      "headSha": "bdba42b600d712acb77926774c75254b8c290ea6",
      "status": "completed",
      "conclusion": "success",
      "createdAt": "2026-04-27T16:35:01Z",
      "url": "https://github.com/happy520ai/unified-ai-system/actions/runs/25007359180"
    },
    "releaseCount": 0,
    "releases": [],
    "laterPhase134ExecutionClosed": true
  },
  "workflow": {
    "path": ".github/workflows/release-gate.yml",
    "forbiddenReleaseOrPublishHits": []
  },
  "docs": {
    "preflightDoc": "docs/RELEASE_PREFLIGHT.md",
    "remoteStatusDoc": "docs/REMOTE_RELEASE_STATUS.md",
    "userManual": "docs/USER_MANUAL.md"
  },
  "safety": {
    "readOnlyPreflight": true,
    "gitTagCreated": false,
    "githubReleaseCreated": false,
    "releaseCreatedByLaterPhase134": true,
    "releaseArtifactUploaded": false,
    "packagePublished": false,
    "dockerImagePublished": false,
    "cloudDeploymentComplete": false,
    "publicProductionDeploymentComplete": false,
    "globalReleaseComplete": false,
    "realAgentExecutionEnabled": false,
    "plaintextApiKeyRecorded": false
  },
  "nextManualDecisions": [
    "choose release version and tag name",
    "decide draft versus prerelease status",
    "write release notes from verified evidence",
    "decide release assets",
    "decide whether package or image publishing belongs in a later phase",
    "rerun the remote Release Gate on the exact release commit"
  ],
  "secretFindingCount": 0,
  "conclusion": "release-artifact-preflight-closed"
}
