{
  "phase": "Phase513A",
  "title": "Yiyi Demo Twelfth Low-risk Auto-run Closure",
  "packageType": "twelfth-low-risk-auto-run-closure",
  "checklist": [
    {
      "id": "twelfthLowRiskClosureCreated",
      "order": 1,
      "status": "prepared",
      "safetyBoundary": "dry-run docs/evidence only; no provider, no secret, no deploy, no billing"
    },
    {
      "id": "phase384StopPrepared",
      "order": 2,
      "status": "prepared",
      "safetyBoundary": "dry-run docs/evidence only; no provider, no secret, no deploy, no billing"
    }
  ],
  "previousClosure": {
    "path": "apps/ai-gateway-service/evidence/phase512/yiyi-demo-lowrisk-extension-index-closure-result.json",
    "exists": true,
    "sizeBytes": 2092
  },
  "phase384StillRequiresHumanApproval": true,
  "providerCallsMade": false,
  "nonNvidiaProviderCallsMade": false,
  "secretValueExposed": false,
  "rawSecretAccessed": false,
  "deployExecuted": false,
  "releaseExecuted": false,
  "tagCreated": false,
  "artifactUploaded": false,
  "approvalForged": false,
  "billingExecuted": false,
  "invoiceGenerated": false,
  "productionGaClaimed": false,
  "workspaceCleanClaimed": false
}
